qubitctrl.cpython-312-darwin.so
qubitctrl.pyi
qubitctrl-0.0.5.dist-info/RECORD
qubitctrl-0.0.5.dist-info/WHEEL
qubitctrl-0.0.5.dist-info/entry_points.txt
qubitctrl-0.0.5.dist-info/top_level.txt
qubitctrl-0.0.5.dist-info/METADATA
qubitctrl-0.0.5.dist-info/licenses/LICENSE
