Metadata-Version: 2.4
Name: qubitctrl
Version: 0.0.5
Summary: qubit controller tool
Author-email: Yaqiang Sun <sunyaking@163.com>
License: GPL-3.0
Requires-Python: <3.13,>=3.12
License-File: LICENSE
Requires-Dist: quarkstudio>=7.1.6
Requires-Dist: quarkcircuit>=0.4.0
Requires-Dist: uv>=0.9.28
Requires-Dist: plotly>=6.5.2
Provides-Extra: full
Requires-Dist: blinker>=1.9.0; extra == "full"
Requires-Dist: ipywidgets>=8.1.7; extra == "full"
Requires-Dist: isort>=6.0.1; extra == "full"
Requires-Dist: notebook==5.7.16; extra == "full"
Requires-Dist: nsqdriver>=0.12.16; extra == "full"
Requires-Dist: numpy==1.26.4; extra == "full"
Requires-Dist: openpyxl>=3.1.5; extra == "full"
Requires-Dist: pandas>=2.3.0; extra == "full"
Requires-Dist: paramiko>=3.5.1; extra == "full"
Requires-Dist: pip>=25.1.1; extra == "full"
Requires-Dist: pyserial>=3.5; extra == "full"
Requires-Dist: pyside6==6.9.0; extra == "full"
Requires-Dist: pyvisa>=1.15.0; extra == "full"
Requires-Dist: pyvisa-py>=0.8.0; extra == "full"
Requires-Dist: qiskit==1.2.4; extra == "full"
Requires-Dist: qiskit-algorithms==0.3.1; extra == "full"
Requires-Dist: qlisp>=1.1.4; extra == "full"
Requires-Dist: qlispc>=1.2.0; extra == "full"
Requires-Dist: qufit>=1.1.65; extra == "full"
Requires-Dist: qulab>=2.12.1; extra == "full"
Requires-Dist: sympy>=1.14.0; extra == "full"
Requires-Dist: systemq; extra == "full"
Requires-Dist: vios>=3.3.2; extra == "full"
Requires-Dist: wath>=1.2.0; extra == "full"
Requires-Dist: waveforms>=2.2.1; extra == "full"
Requires-Dist: yapf>=0.43.0; extra == "full"
Requires-Dist: h5py>=3.15.1; extra == "full"
Requires-Dist: zee>=0.0.4; extra == "full"
Requires-Dist: vispy>=0.16.1; extra == "full"
Requires-Dist: pyqtgraph>=0.14.0; extra == "full"
Dynamic: license-file
